{
    "experiment_name": "run_2025_12_27_giraffe_baseline_v1",
    "timestamp": "2025-12-27 10:11:07",
    "model_architecture": {
        "class_name": "GiraffeBaseline",
        "total_parameters": 5785607,
        "trainable_parameters": 5785607,
        "input_dim": 768,
        "output_dim": 7,
        "structure_summary": "GiraffeBaseline(\n  (network): Sequential(\n    (0): Linear(in_features=768, out_features=2048, bias=True)\n    (1): ReLU()\n    (2): Linear(in_features=2048, out_features=2048, bias=True)\n    (3): ReLU()\n    (4): Linear(in_features=2048, out_features=7, bias=True)\n  )\n)"
    },
    "datasets": {
        "train": "./dataset_processed/chess_bitboard_train.npz",
        "val": "./dataset_processed/chess_bitboard_val.npz",
        "test": "./dataset_processed/chess_bitboard_test.npz"
    },
    "hyperparameters": {
        "epochs": 100,
        "batch_size": 2048,
        "learning_rate": 0.001,
        "optimizer": "Adam",
        "input_shape": 768,
        "output_shape": 7
    },
    "device": "NVIDIA GeForce RTX 3070"
}